MANIFEST.in
README.rst
setup.py
httpkom/__init__.py
httpkom/__main__.py
httpkom/conferences.py
httpkom/errors.py
httpkom/komserialization.py
httpkom/memberships.py
httpkom/misc.py
httpkom/persons.py
httpkom/server.py
httpkom/sessions.py
httpkom/stats.py
httpkom/texts.py
httpkom/version.py
httpkom.egg-info/PKG-INFO
httpkom.egg-info/SOURCES.txt
httpkom.egg-info/dependency_links.txt
httpkom.egg-info/not-zip-safe
httpkom.egg-info/requires.txt
httpkom.egg-info/top_level.txt
httpkom/templates/index.html