Metadata-Version: 2.1
Name: httpkom
Version: 0.21
Summary: REST-like HTTP API for LysKOM
Home-page: https://github.com/osks/httpkom
Author: Oskar Skoog
Author-email: oskar@osd.se
License: UNKNOWN
Platform: UNKNOWN
Classifier: License :: OSI Approved :: GNU General Public License v2 or later (GPLv2+)
Requires-Python: >=3.7
